Workbook
Name aporte: Investimentos!$E$23
Name patrimonio: Investimentos!$E$26
Name qtd_anos: Investimentos!$E$24
Name rendimento_carteira: Investimentos!$E$17
Name salario: Investimentos!$E$16
Name sugestao_investimento: Investimentos!$E$18
Name taxa_mensal: Investimentos!$E$25

Sheet Investimentos
G2: PROJEÇÃO MENSAL (APÓS 5 ANOS)
G3: =E27/(1+E19)^qtd_anos -> 502.66148
G8: PATRIMÔNIO (APÓS 5 ANOS)
G9: =patrimonio -> 83776.914
B15: CONFIGURAÇÕES
B16: Salário | E16: 5000
B17: Rendimento da carteira | E17: 0.006
B18: Sugestão de investimento (30 % do valor do salário) | E18: =E16*30% -> 1500
B22: INVESTIMENTO MENSAL
B23: Quanto investir por mês? | E23: 1000
B24: Por quantos anos? | E24: 5
B25: Taxa de rendimento mensal? | E25: 0.01079
B26: Patrimônio acumulado? | E26: =FV(E25,E24*12,E23*-1) -> 83776.914
B27: Dividendos Mensais? | E27: =patrimonio*$E$17 -> 502.66148
B29: CENÁRIOS | E29: DIVIDENDOS
A30: 2 | B30: Quanto em 2 anos? | C30: =FV($E$25,$A30*12,$E$23*-1) -> 27227.627 | E30: =C30*$E$17 -> 163.36576
A31: 5 | B31: Quanto em 5 anos? | C31: =FV($E$25,$A31*12,$E$23*-1) -> 83776.914 | E31: =C31*$E$17 -> 502.66148
A32: 10 | B32: Quanto em 10 anos? | C32: =FV($E$25,$A32*12,$E$23*-1) -> 243284.21 | E32: =C32*$E$17 -> 1459.7053
A33: 20 | B33: Quanto em 20 anos? | C33: =FV($E$25,$A33*12,$E$23*-1) -> 1125198.4 | E33: =C33*$E$17 -> 6751.1904
A34: 30 | B34: Quanto em 30 anos? | C34: =FV($E$25,$A34*12,$E$23*-1) -> 4322169.7 | E34: =C34*$E$17 -> 25933.018
B37: PERFIL | E37: MODERADO
B38: VALOR A SER INVESTIDO POR MÊS | E38: =aporte -> 1000
B40: TIPO DE FII | C40: Percentual sugerido | D40: Valores
B41: PAPEL | C41: =VLOOKUP($E$37&"-"&B41,Planilha2!$B:$E,4,FALSE) -> 0.32 | E41: =C41*$E$38 -> 320
B42: TIJOLO | C42: =VLOOKUP($E$37&"-"&B42,Planilha2!$B:$E,4,FALSE) -> 0.35 | E42: =C42*$E$38 -> 350
B43: HÍBRIDOS | C43: =VLOOKUP($E$37&"-"&B43,Planilha2!$B:$E,4,FALSE) -> 0.08 | E43: =C43*$E$38 -> 80
B44: FOFs | C44: =VLOOKUP($E$37&"-"&B44,Planilha2!$B:$E,4,FALSE) -> 0.05 | E44: =C44*$E$38 -> 50
B45: DESENVOLVIMENTO | C45: =VLOOKUP($E$37&"-"&B45,Planilha2!$B:$E,4,FALSE) -> 0.1 | E45: =C45*$E$38 -> 100
B46: HOTELARIA | C46: =VLOOKUP($E$37&"-"&B46,Planilha2!$B:$E,4,FALSE) -> 0.1 | E46: =C46*$E$38 -> 100
E47: =SUM(E41:E46) -> 1000
B64: Desenvolvido por Michele | Baseado no modelo do Bootcamp Santander- Excel com IA e Claude | © 2026

Sheet Planilha2
B4: CHAVE | D4: TIPO DE FII | E4: Percentual
B5: =C5&"-"&D5 -> CONSERVADOR-PAPEL | C5: CONSERVADOR | D5: PAPEL | E5: 0.3
B6: =C6&"-"&D6 -> CONSERVADOR-TIJOLO | C6: CONSERVADOR | D6: TIJOLO | E6: 0.5
B7: =C7&"-"&D7 -> CONSERVADOR-HÍBRIDOS | C7: CONSERVADOR | D7: HÍBRIDOS | E7: 0.1
B8: =C8&"-"&D8 -> CONSERVADOR-FOFs | C8: CONSERVADOR | D8: FOFs | E8: 0.1 | G8: MODERADO-TIJOLO | I8: =VLOOKUP(G8,$B:$E,4,FALSE) -> 0.35
B9: =C9&"-"&D9 -> CONSERVADOR-DESENVOLVIMENTO | C9: CONSERVADOR | D9: DESENVOLVIMENTO | E9: 0
B10: =C10&"-"&D10 -> CONSERVADOR-HOTELARIA | C10: CONSERVADOR | D10: HOTELARIA | E10: 0
B11: =C11&"-"&D11 -> MODERADO-PAPEL | C11: MODERADO | D11: PAPEL | E11: 0.32
B12: =C12&"-"&D12 -> MODERADO-TIJOLO | C12: MODERADO | D12: TIJOLO | E12: 0.35
B13: =C13&"-"&D13 -> MODERADO-HÍBRIDOS | C13: MODERADO | D13: HÍBRIDOS | E13: 0.08
B14: =C14&"-"&D14 -> MODERADO-FOFs | C14: MODERADO | D14: FOFs | E14: 0.05
B15: =C15&"-"&D15 -> MODERADO-DESENVOLVIMENTO | C15: MODERADO | D15: DESENVOLVIMENTO | E15: 0.1
B16: =C16&"-"&D16 -> MODERADO-HOTELARIA | C16: MODERADO | D16: HOTELARIA | E16: 0.1
B17: =C17&"-"&D17 -> AGRESSIVO-PAPEL | C17: AGRESSIVO | D17: PAPEL | E17: 0.5
B18: =C18&"-"&D18 -> AGRESSIVO-TIJOLO | C18: AGRESSIVO | D18: TIJOLO | E18: 0.1
B19: =C19&"-"&D19 -> AGRESSIVO-HÍBRIDOS | C19: AGRESSIVO | D19: HÍBRIDOS | E19: 0.05
B20: =C20&"-"&D20 -> AGRESSIVO-FOFs | C20: AGRESSIVO | D20: FOFs | E20: 0.05
... B22: =C22&"-"&D22 -> AGRESSIVO-HOTELARIA | C22: AGRESSIVO | D22: HOTELARIA | E22: 0.1
